pybadger/__init__.py
pybadger/badge.py
pybadger/badger.py
pybadger/protocol.py
pybadger/pepy/__init__.py
pybadger/pepy/badge.py
pybadger/pepy/badger.py
pybadger/pepy/pypi.py
pybadger/shields/__init__.py
pybadger/shields/badge.py
pybadger/shields/badger.py
pybadger/shields/binder.py
pybadger/shields/codecov.py
pybadger/shields/conda.py
pybadger/shields/discord.py
pybadger/shields/github.py
pybadger/shields/librariesio.py
pybadger/shields/pepy.py
pybadger/shields/pypi.py
pybadger/shields/readthedocs.py
pybadger/shields/repodynamics.py
pybadger-0.1.0.dist-info/METADATA
pybadger-0.1.0.dist-info/WHEEL
pybadger-0.1.0.dist-info/top_level.txt
pybadger-0.1.0.dist-info/RECORD
